cubit/__init__.py
cubit/async_client.py
cubit/client.py
cubit/exceptions.py
cubit/models.py
cubit/py.typed
cubit_api-0.2.1.dist-info/METADATA
cubit_api-0.2.1.dist-info/WHEEL
cubit_api-0.2.1.dist-info/licenses/LICENSE
cubit_api-0.2.1.dist-info/RECORD
