Metadata-Version: 2.4
Name: cubit-api
Version: 0.2.1
Summary: Python SDK for the Cubit API - AI Job Vulnerability Intelligence
Project-URL: Homepage, https://maidenlabs.org
Author-email: Maiden Labs <tim@maidenlabs.org>
License-Expression: MIT
License-File: LICENSE
Keywords: ai,api,automation,cubit,jobs,labor-market,sdk
Classifier: Development Status :: 4 - Beta
Classifier: Intended Audience :: Developers
Classifier: License :: OSI Approved :: MIT License
Classifier: Operating System :: OS Independent
Classifier: Programming Language :: Python :: 3
Classifier: Programming Language :: Python :: 3.8
Classifier: Programming Language :: Python :: 3.9
Classifier: Programming Language :: Python :: 3.10
Classifier: Programming Language :: Python :: 3.11
Classifier: Programming Language :: Python :: 3.12
Classifier: Typing :: Typed
Requires-Python: >=3.8
Requires-Dist: httpx>=0.24.0
Provides-Extra: dev
Requires-Dist: pytest-asyncio>=0.21.0; extra == 'dev'
Requires-Dist: pytest>=7.0.0; extra == 'dev'
Requires-Dist: respx>=0.20.0; extra == 'dev'
